[
  {
    "idiom":"Absence makes the heart grow fonder. ",
    "definition":"Being far away from someone makes you love them more."
  },
  {
    "idiom":"Don't rain on my parade. ",
    "definition":"If I'm happy, don't try to make me sad. "
  },
  {
    "idiom":"Don't count your chickens before they hatch. ",
    "definition":"Don't be too sure that something you hope for will really happen. "
  },
  {
    "idiom":"Let's hit the road! ",
    "definition":"It's time to begin our journey. "
  },
  {
    "idiom":"Better safe than sorry. ",
    "definition":"It's better to be extremely careful than to make a dangerous mistake. "
  },
  {
    "idiom":"The ball is in your court. ",
    "definition":"It's your turn to make a decision. "
  },
  {
    "idiom":"Actions speak louder than words. ",
    "definition":"What you do is more important than what you say. "
  },
  {
    "idiom":"You're barking up the wrong tree. ",
    "definition":"You're looking in the wrong place. "
  },
  {
    "idiom":"The ball is in your court. ",
    "definition":"It's your turn to make a decision. "
  },
  {
    "idiom":"It's time to go back to the drawing board. ",
    "definition":"Our plan didn't work, so we have to start over. "
  },
  {
    "idiom":"It's the best thing since sliced bread. ",
    "definition":"It's an amazing new invention. "
  },
  {
    "idiom":"Don't bite off more than you can chew. ",
    "definition":"Don't agree to do more work than you can handle. "
  },
  {
    "idiom":"You can't judge a book by its cover. ",
    "definition":"You can't tell what something is like based only on its appearance. "
  },
  {
    "idiom":"It costs an arm and a leg. ",
    "definition":"It's extremely expensive. "
  },
  {
    "idiom":"It's no use crying over spilled milk. ",
    "definition":"There's not reason to stay upset about something that happened in the past . "
  }
]
